dev_shell/__init__.py
dev_shell/__main__.py
dev_shell/base_cmd2_app.py
dev_shell/bootstrap-source.py
dev_shell/config.py
dev_shell/constants.py
dev_shell/dev_shell_app.py
dev_shell/command_sets/__init__.py
dev_shell/command_sets/dev_shell_commands.py
dev_shell/tests/__init__.py
dev_shell/tests/constants.py
dev_shell/tests/fixtures.py
dev_shell/tests/test_bootstrap.py
dev_shell/tests/test_dev_shell_app.py
dev_shell/tests/test_doctests.py
dev_shell/tests/test_project_setup.py
dev_shell/tests/test_source_file.py
dev_shell/tests/utils.py
dev_shell/utils/__init__.py
dev_shell/utils/assertion.py
dev_shell/utils/colorful.py
dev_shell/utils/subprocess_utils.py
dev_shell-0.9.1.dist-info/LICENSE
dev_shell-0.9.1.dist-info/METADATA
dev_shell-0.9.1.dist-info/WHEEL
dev_shell-0.9.1.dist-info/entry_points.txt
dev_shell-0.9.1.dist-info/top_level.txt
dev_shell-0.9.1.dist-info/RECORD
