Metadata-Version: 2.2
Name: dev-shell
Version: 0.9.1
Summary: Developer shell for easy startup...
Author-email: Jens Diemer <dev-shell@jensdiemer.de>
License: GPL-3.0-or-later
Project-URL: Documentation, https://github.com/jedie/dev-shell
Project-URL: Source, https://github.com/jedie/dev-shell
Requires-Python: >=3.11
License-File: LICENSE
Requires-Dist: cmd2
Requires-Dist: cli-base-utilities
